{"cameraMode":{"drawMode":0,"name":"Shaded","section":"Shading Mode"},"sceneLighting":true,"audioPlay":false,"sceneViewState":{"showFog":true,"showMaterialUpdate":false,"showSkybox":true,"showFlares":true,"showImageEffects":true,"showParticleSystems":true},"in2DMode":false,"pivot":{"x":790.5030517578125,"y":-485.4635009765625,"z":232.384765625},"rotation":{"x":-0.014345415867865086,"y":0.8430493474006653,"z":-0.5371739268302918,"w":-0.022514110431075097},"size":2835.983642578125,"orthographic":false}